nkflow/__init__.py
nkflow/nkflow.py
nkflow-0.1.0.dist-info/licenses/LICENSE
nkflow-0.1.0.dist-info/METADATA
nkflow-0.1.0.dist-info/WHEEL
nkflow-0.1.0.dist-info/top_level.txt
nkflow-0.1.0.dist-info/RECORD
