Metadata-Version: 2.4
Name: nkflow
Version: 0.1.0
Summary: Generate, save, and optionally run AI-generated code using LangChain LLMs.
Author: Nitin Kaira
Author-email: Nitin Kaira <nkaira784@gmail.com>
License: MIT License
Requires-Python: >=3.10
License-File: LICENSE
Requires-Dist: langchain
Requires-Dist: langchain-google-genai
Requires-Dist: langchain-openai
Dynamic: author
Dynamic: license-file
Dynamic: requires-python
